Workbook

Sheet 校稿總覽與統計
B2: 工作的管見（My Two Cents） — 職場生存與成長的避坑指南
B3: 英文・中文・台文 三語對照校稿手冊（Excel 試算校對版） | 產出時間：2026-10-17 07:23
B5: 【校稿操作指引與使用說明】
B6: 1. 本校稿工作表完整收錄全書 458 條實務原則卡牌、20 大核心原則與 53 則篇章金句，專為三語精準對照、審定與批註修訂設計。
B7: 2. 校稿狀態選單：請在各工作表之「校對狀態」欄位點選下拉選單，選取：【通過】、【待修】、【已修訂】、【有疑問】、【未校對】。
B8: 3. 狀態顏色高亮：選取狀態後儲存格自動變色（綠色=通過、紅色=待修、藍色=已修訂、黃色=有疑問），視覺化追蹤極為直覺。
B9: 4. 即時統計儀表板：下方表格會依據您在各工作表填寫的校對狀態，自動透過 Excel 公式計算通過率與剩餘待審項目。
B10: 5. 凍結窗格與篩選：各工作表首列已鎖定標題列，並已啟用自動篩選 (AutoFilter)，方便隨時依投影片或校對狀態快速篩選。
B12: ■ 全書三語校對進度儀表板 (即時公式動態統計)
B13: 項目類別 (Category) | C13: 收錄總數 (Total) | D13: 審定通過 (Passed) | E13: 待修訂 (Needs Fix) | F13: 已修訂 (Revised) | G13: 有疑問 (Questions) | H13: 未校對 (Unchecked) | I13: 完成進度 (Progress)
B14: 實務原則卡牌（458 條） | C14: =COUNTA('實務原則卡牌校對 (458條)'!B2:B459) | D14: =COUNTIF('實務原則卡牌校對 (458條)'!H2:H459, "通過") | E14: =COUNTIF('實務原則卡牌校對 (458條)'!H2:H459, "待修") | F14: =COUNTIF('實務原則卡牌校對 (458條)'!H2:H459, "已修訂") | G14: =COUNTIF('實務原則卡牌校對 (458條)'!H2:H459, "有疑問") | H14: =C14-D14-E14-F14-G14 | I14: =(D14+F14)/C14
B15: 20 大核心原則 | C15: =COUNTA('20大核心原則校對'!C2:C21) | D15: =COUNTIF('20大核心原則校對'!I2:I21, "通過") | E15: =COUNTIF('20大核心原則校對'!I2:I21, "待修") | F15: =COUNTIF('20大核心原則校對'!I2:I21, "已修訂") | G15: =COUNTIF('20大核心原則校對'!I2:I21, "有疑問") | H15: =C15-D15-E15-F15-G15 | I15: =(D15+F15)/C15
B16: 篇章核心指引金句（53 則） | C16: =COUNTA('篇章核心指引金句 (53則)'!C2:C54) | D16: =COUNTIF('篇章核心指引金句 (53則)'!E2:E54, "通過") | E16: =COUNTIF('篇章核心指引金句 (53則)'!E2:E54, "待修") | F16: =COUNTIF('篇章核心指引金句 (53則)'!E2:E54, "已修訂") | G16: =COUNTIF('篇章核心指引金句 (53則)'!E2:E54, "有疑問") | H16: =C16-D16-E16-F16-G16 | I16: =(D16+F16)/C16
B17: 全書合計 (Overall Total) | C17: =SUM(C14:C16) | D17: =SUM(D14:D16) | E17: =SUM(E14:E16) | F17: =SUM(F14:F16) | G17: =SUM(G14:G16) | H17: =SUM(H14:H16) | I17: =(D17+F17)/C17
B19: 【工作表快速導覽】
B20: • 『實務原則卡牌校對 (458條)』工作表：完整 458 條原則卡牌，包含投影片頁次、原文、優化英中台三語與批註欄。
B21: • 『20大核心原則校對』工作表：全書 20 大核心原則，依六大篇章分類對照，含對應實務卡牌編號清單。
B22: • 『篇章核心指引金句 (53則)』工作表：六大篇章之 53 則引導星號金句，審閱精準度與文化語韻。

Sheet 實務原則卡牌校對 (458條)
A1: 投影片 | B1: 卡牌編號 | C1: 關聯核心原則 | D1: 投影片原文 (Slide Original) | E1: 優化英文 (Polished English) | F1: 優化中文 (Polished Mandarin) | G1: 優化台文 (Polished Taiwanese) | H1: 校對狀態 | I1: 修訂建議與批註 | J1: 校對人 | K1: 校對日期
A2: Slide 1 | B2: No. 1 | C2: 原則 1, 原則 2 | D2: Add your leave and personal work time, even business trip and national holiday in the calendar. Automatic email replies. Request to resend the email. When you back to office, your colleagues can set delayed delivery for email sending on certain date. Item 82. Plan in the canlender. | E2: Block out all leave, personal work time, business trips, and national holidays in your calendar. Set up automatic out-of-office email replies (prompting senders to follow up upon your return if needed). When you return, colleagues can use delayed email delivery to stagger messages. Plan everything directly in your calendar (refer to Item 82). | F2: 在行事曆中完整排定假勤、個人專注工作時間、出差與國定假日。同步設定電子郵件自動回覆（可提醒寄件者於返工後再發送），同仁亦可利用預約定時寄件功能於特定日期遞送郵件。養成將所有工作與休假妥善規劃於行事曆中的習慣（參見第 82 項）。 | G2: 共請假、家己專注做工的時間、出差佮國定節日攏排入行事曆。電子信設好自動回覆（請人等你轉來才閣重寄）。轉來公司了後，同仁嘛會用得設預約寄信。代誌佇行事曆先排好勢，才袂手忙跤亂、掠無頭總（參照第 82 項）。
A3: Slide 1 | B3: No. 2 | C3: 原則 9 | D3: Ask politely with reason and watch out your voice tone. Soft skills related to how to communicate and ask. ( rephrase if needed) | E3: Communicate requests politely by providing clear rationale while monitoring your tone of voice. Mastering these soft skills ensures effective and harmonious professional communication. | F3: 提問或要求時應禮貌並說明具體原因，同時注意說話的語氣與聲調。掌握這類溝通與表達的軟實力，能讓職場互動更加順暢與和諧。 | G3: 拜託人抑是問代誌愛客氣有禮數，共因由講清楚，講話聲調佮氣口愛斟酌（看情形換較順耳的講法）。掌握溝通問話的軟實力，手腕幼路，代誌才好參詳。
A4: Slide 1 | B4: No. 3 | C4: 原則 10 | D4: Prepare questions during the meeting. // Understand agenda and what is the potential / desired outcome to make. (OKR)，" 自由人" → ask good question to yourself | E4: Prepare thoughtful questions prior to or during meetings by understanding the agenda and desired outcomes (aligning with OKRs). As an autonomous professional, continuously ask yourself sharp questions to drive clarity. | F4: 開會前與會議中應預先準備好問題，充分理解會議議程與預期目標（結合 OKR 思考）。作為一位自主獨立的專業人士，更要養成向自己提出好問題的習慣。 | G4: 開會進前佮開會時問題先備便，共議程佮預期成果想透徹（配合 OKR 盤算）。做一个主動自立的「自由人」，平素時就定定問家己關鍵的好問題。
A5: Slide 1 | B5: No. 4 | C5: 原則 1, 原則 19, 原則 20 | D5: Reserve some buffer for your project, and your sacred time or place. (margin of safety),spend time on your investment, rest, and kinds and family. It is part of investment portfolio. How to use your time. Use scared time for enhancing capability.減法思維，熱情思維，抓大魚，能量管理 | E5: Reserve buffer time for your projects, establishing a "sacred time and place" (a margin of safety) to focus on self-investment, rest, hobbies, and family. Treat time allocation as an investment portfolio. Use your sacred time to enhance your capabilities. (Mindset of subtraction, passion, focus on high-impact tasks, and energy management) | F5: 為專案保留緩衝空間，建立個人的「神聖時間與空間」（安全邊際），用以投資自我、休息與陪伴家人。將時間視為投資組合，利用不被打擾的神聖時間提升自我能力。（實踐減法思維、熱情思維、抓大魚法則與能量管理） | G5: 專案愛留一寡緩衝，留家己的「神聖時間佮所在」（安全邊際），用來投資家己、歇睏佮陪囡仔、厝內人。時間分配當做投資組合，趁無人吵的神聖時間鍛鍊真本領。（減法思維、熱情思維、掠大魚、顧元氣）
A6: Slide 1 | B6: No. 5 | C6: 原則 18 | D6: Don't jump to conclusions too soon. You may use your lizard brain to act. Instinct react is not good. Be humble. You may get wrong. 心理偏見清單 | E6: Avoid rushing to hasty conclusions driven by instinct or the "lizard brain." Maintain humility and acknowledge that your initial impression could be flawed; keep a mental bias checklist handy. | F6: 切忌過早下定論，避免任由蜥蜴腦（本能衝動）來主導反應。保持謙遜，意識到自己也可能犯錯，並對常見的心理偏見保持警覺。 | G6: 做代誌莫趕緊落定論，莫順著本能（四跤蛇腦）衝動反應。人愛謙虛，愛記持家己嘛會看走眼，心肝頭備一張「心理偏見清單」，防範想毋著走偏去。
A7: Slide 1 | B7: No. 6 | C7: 原則 1, 原則 20 | D7: Smile Always smile. A friend is better than an enemy. Peace. Stay calm (not impluse) in any direction. breath inhaule,hold, exhaule, hold. | E7: Always maintain a smile; dynamic cooperation is always better than friction. Stay calm and deliberate in all circumstances. Practice box breathing (inhale, hold, exhale, hold) to regulate your emotions under pressure. | F7: 保持微笑，多一個朋友少一個敵人。無論面對何種局勢，都要保持冷靜與克制，切勿衝動行事。可透過正念呼吸（吸氣、憋氣、呼氣、憋氣）來穩定情緒。 | G7: 面頂定定帶笑容，加一个朋友減一个冤仇人，以和為貴。無論拄著啥物風波攏愛沉穩莫衝動。心煩時做四方呼吸（吸氣、憋氣、吐氣、憋氣），氣順心就平。
A8: Slide 1 | B8: No. 7 | C8: 原則 10 | D8: Ask effective questions in meetings. It is best to prepare a list of questions in advanced. Item3. | E8: Ask high-impact questions in meetings. It is best to prepare a list of questions in advance. (Related to Item 3) | F8: 在會議中提出有效的問題。最理想的做法是提前準備好問題清單。 | G8: 開會發問愛問著重點、問入骨。上好佇開會進前就共問題清單先備好勢。（參照第 3 項）
A9: Slide 1 | B9: No. 8 | C9: 原則 4 | D9: Collect thank you notes for your KPI and achievement… Documentation, naming rules. Mise en place. | E9: Collect appreciation emails and thank-you notes to support your KPI reviews and achievements. Practice neat documentation, consistent naming conventions, and professional preparation (Mise en place). | F9: 收集來自同事或客戶的感謝信，作為 KPI 考評與成就證明的佐證。落實文件化管理、統一命名規範，做好隨時備用的準備工作（Mise en place）。 | G9: 別人寄予你的感謝批愛收留好勢，當做拍考績（KPI）佮實績的鐵證。檔案照命名規矩存好，手尾備齊（Mise en place），欲用的時陣隨時揣會著。
A10: Slide 1 | B10: No. 9 | C10: 原則 13 | D10: Don't be jealous of your colleagues and don't treat them as your best friends, especially when personal interests conflict. Don’t add them in your social media APP, only in Linkedin. To set privacy for friends only. Don’t make joke who you may not know you well. To learn from your colleagues, no matter how old is he or she. Don’t do political judge. | E10: Avoid being jealous of colleagues and do not treat them as best friends, especially since personal interests may conflict. Connect only via LinkedIn rather than private social media (which should have privacy settings set to friends only). Avoid joking with people you do not know well. Always learn from your colleagues, regardless of age, and remain politically neutral. | F10: 不要嫉妒同事，也別把同事當成最好的朋友（特別是當利益衝突時）。避免在私人的社群媒體加同事，僅用 LinkedIn 聯絡並確保私人社群的隱私設定。不要對不熟的人開玩笑。不論年資深淺，都要抱持學習態度，且避免進行辦公室政治評判。 | G10: 莫怨妒同仁，嘛莫共同仁當做換帖的知己（牽涉著個人利益的時陣特別愛斟酌）。私底下的社群軟體莫加同仁，頂多用 LinkedIn 聯絡，私人社群權限設做朋友限定。無熟似的人莫含伊講笑詼。無論對方年歲大細攏有長處好學，千萬莫批評政治抑是插手公司派系。
A11: Slide 1 | B11: No. 10 | C11: 原則 12 | D11: Determine what your priorities are now. Distinguish between what you cannot control and what you can control. Item 141. And focus on what you can control and ask for help/support for what you cannot control. Item 141. | E11: Identify your current priorities. Learn to distinguish between what you can control and what you cannot. Focus your energy on things under your control, and proactively seek support for things you cannot control. (Related to Item 141) | F11: 明確當下的首要任務。區分「可控」與「不可控」的事物。將精力集中於可控的事，對於不可控的事物則應適時尋求外部支援與協助。 | G11: 先分清這馬上要緊的代誌。分清楚啥物是家己控制會著的、啥物是控制袂著的。精神氣力攏集中佇控制會著的代誌，控制袂著的就主動開喙請人鬥相共。（參照第 141 項）
A12: Slide 1 | B12: No. 11 | C12: 原則 9 | D12: Check your spelling before sending the email. Using Google translate or Grammarly or using mandarin directly for urgent cases to avoid confusion and misunderstanding. There is a website to check grammar. | E12: Check your spelling and grammar (using tools like Google Translate or Grammarly) before sending emails. For urgent cases, writing in Mandarin directly is better than sending confusing English emails. | F12: 發信前務必檢查拼字與文法（可善用 Grammarly 等工具）。若是十萬火急的情況，直接寫中文也比發一封文法混亂、容易引起誤會的英文信來得妥當。 | G12: 寄信進前先巡看覓字敢有寫對、文法敢有順（會使借 Google 翻譯抑是 Grammarly 鬥相共檢查）。若拄著十萬火急的代誌，直接寫中文，嘛贏過寄一封文理不通、予人誤會的英文信。
A13: Slide 1 | B13: No. 12 | C13: 原則 15, 原則 16 | D13: Make sure you learn something during the project and document it. These skills/things will boost you or feedback or whatever adds value from long-term view. | E13: Ensure you learn something from every project and document the knowledge. These accumulated skills and feedback will boost your career and add significant long-term value. | F13: 確保自己能從每個專案中學到東西並記錄下來。這些累積的技能與反饋從長期來看，會成為提升自我價值的推進器。 | G13: 確保逐个專案攏有學著新眉角，閣愛筆記落來。這寡累積的工夫佮回饋，就長遠來看，攏是替家己添身價的好本底。
... A381: Slide 8 | B381: No. 376 | C381: 原則 6, 原則 11 | D381: Stop telling people more than they need to know. P457 | E381: Practice information restraint: avoid sharing details beyond what is strictly necessary for the audience and objective. | F381: 學會資訊節制，切勿透露超出對方所需知悉範圍之外的冗餘細節。 | G381: 開喙講話愛知輕重節制，對方無需要知影的冗雜細節，就莫講傷濟，話留三分才袂招惹麻煩。（對照第 457 條）
A382: Slide 8 | B382: No. 377 | C382: 原則 2 | D382: => don't reply email after 3:00 PM if it is not necessary. spend time on real output, learn new things/growth, documentation...etc. habit, positive words,=> just fine....just good. | E382: Unless urgent, avoid replying to non-critical emails after 3:00 PM. Instead, dedicate late afternoons to high-impact outputs, documentation, and skill acquisition. Build positive daily habits and maintain an optimistic mindset (e.g., framing outcomes as 'just fine' or 'good progress'). | F382: 非必要時，過午後三點應減少回覆非緊急郵件，將寶貴時間投入於實質產出、文件歸檔與自我進修。培養良好的正向習慣與心態（如以「挺好、順利」來積極看待成果）。 | G382: 若無火燒罟寮的急事，下晡三點了後莫一直回電郵。共光陰提去做真正有產出的好代誌、整理檔案抑是進修。養成好習慣，定定用正面的話互相鼓勵，心頭自在就真好。
A383: Slide 8 | B383: No. 378 | C383: 原則 9, 原則 11 | D383: I am driving this activity with low priority in my daily to do list. Hope to get is done by end of September. Could you please let me know more background of your question, any need to change my to do list priority. Way to request. | E383: Use diplomatic phrasing for priority negotiation: "I am currently tracking this task with lower priority on my backlog, aiming for completion by late September. Could you share more background on this request so I can evaluate if we need to adjust priorities?" | F383: 優雅談判優先順序話術：「我目前將此項任務排在待辦清單中較低優先級，預計在九月底前完成。能否請您提供更多背景資訊，以便我評估是否需要調整目前的任務優先順序？」 | G383: 應對優先順序的體面講法：「這項任務我目前排佇排程內底較後壁的位，預計九月底前做煞。敢會當請你多補充一寡背景資訊，予我評估敢有需要調動先後次序？」
A384: Slide 8 | B384: No. 379 | C384: 原則 17 | D384: always ready to leave Your current position. And learn a survival skill to work anywhere. Always pay you first. The abilities you can take away. | E384: Always maintain career mobility by being ready to change roles. Focus on mastering portable, core professional skills that guarantee your value anywhere, and invest in yourself first. | F384: 隨時保持隨時能離職轉身的實力。專注於鍛造帶得走的通用核心專業技能，確保無論身在何處都能獨立立足；投資自己永遠是第一優先。 | G384: 時時刻刻做足隨時會當離職轉身的底氣。愛練就行到佗位攏有法度靠伊食飯的真功夫；共時間佮心力投資佇家己紮會走的本事頂高，永遠排第一。
A385: Slide 8 | B385: No. 380 | C385: 原則 19, 原則 20 | D385: Prepare 1 min actions. As part of sense of ritual.Deep breath. | E385: Design 1-minute warm-up rituals—such as taking a deep breath—to create a sense of transition and focus before launching into key tasks. | F385: 建立一分鐘儀式感動作（例如深呼吸），為轉化工作狀態與高度專注打造良好的開端。 | G385: 替家己安排一个一分鐘的「儀式」動作（親像深呼吸），安定心神、收煞雜念，順暢切換到專注做代誌的境界。
A386: Slide 8 | B386: No. 381 | C386: 原則 18 | D386: In any situation, stay calm. Item388. | E386: In any situation, maintain your composure and stay calm. (Related to Item 388) | F386: 不論面對何種突發狀況，務必保持冷靜與克制。（對照第388條） | G386: 無論拄著啥物大風大浪抑是突發狀況，心神千萬愛定，保持冷靜佮沉穩。（對照第 388 條）
A387: Slide 8 | B387: No. 382 | C387: 原則 6, 原則 17 | D387: Learn read financial report from top managers and annual report for considering job security, what is the KPI for coming year. How to judge operation working fine or not. To see if your product is survived in the market? What is product life? Cycle time. | E387: Learn to read executive financial summaries and annual reports to evaluate company stability, identify key performance indicators (KPIs) for the upcoming year, and assess operational health. Analyze whether your product holds market longevity, understanding its life cycle and production lead times. | F387: 學會解讀高層財務報告與公司年報，以評估企業營運風險、掌握年度關鍵績效指標（KPI）及判斷整體經營健康度。同時審視產品在市場上的競爭力、生命週期與作業週期。 | G387: 愛學會曉看高層財報佮公司年報，判斷公司體質敢有勇健、來年 KPI 是啥，家己的飯碗敢會安穩。同時審視產品佇市場頂的競爭力、壽命佮生產週期。
A388: Slide 8 | B388: No. 383 | C388: 原則 3, 原則 4 | D388: Don’t hesitate to use new tool or afraid of. Like Chatgpt, 電子筆記。And think where to find it next time quickly. Automation | E388: Embrace modern technology and tools (such as ChatGPT, electronic note-taking apps, and automation workflow tools) without fear. Systematize your information architecture so you can retrieve files quickly when needed. | F388: 勇於擁抱新工具與新技術（如 ChatGPT、數位筆記與自動化工具），切勿排斥。同時建構清晰的資訊檢索邏輯，確保日後能快速查閱與複用。 | G388: 莫驚用新工具佮新科技（親像 ChatGPT、數位筆記佮自動化機制）。整理出清楚的檔案目錄，下一回需要用著的時陣，隨時揣會著、好調度。
A389: Slide 8 | B389: No. 384 | C389: 原則 2, 原則 10 | D389: don’t ask if you may know possible feedback or answers. | E389: Do not ask questions if you already know the answers or can predict the feedback; avoid wasting valuable communication bandwidth. | F389: 如果你已經知道答案或能預測對方的反饋，就別開口詢問，不要浪費多餘的溝通頻寬。 | G389: 家己明明知影答案、抑是早就會當臆出對方的回應，就莫閣開喙多問，莫白白討債雙方的溝通時間。
A390: Slide 8 | B390: No. 385 | C390: 原則 2 | D390: Reduced email communication, talk directly if needed. | E390: Minimize email communication; pick up the phone or speak directly to resolve issues faster. (Related to Item 18) | F390: 減少來回的電子郵件溝通。必要時直接通話或當面討論以提高效率。 | G390: 減少批信來來去去，該當見面抑是敲電話直接講，就當面溝通，才袂共時間耗佇文字往來頂高。
A391: Slide 8 | B391: No. 386 | C391: 原則 16 | D391: Secure circle of power and extent it. Review your skill table. | E391: Consolidate your core circle of competence (power of circle) first, then expand it. Review your skill matrix periodically. | F391: 先鞏固好你的核心技能圈與影響力邊界，再逐步對外擴張。定期檢視你的個人技能矩陣。 | G391: 先共家己的核心本事佮話事權的界線顧好勢，才一步一步向外開拓。定時盤點家己的技能清單，知長短、補不足。
A392: Slide 8 | B392: No. 387 | C392: 原則 14 | D392: Keep silence till you meet your goal. Keep your mouth shout. | E392: Keep your plans quiet and remain silent until you reach your goal. | F392: 在達成目標之前，保持絕對的低調與沉靜，少說多做。 | G392: 佇目標猶未達成進前，共喙罨好勢，恬恬踏實去做。少膨風、多做代誌，等做成了後才予成果講話。
A393: Slide 8 | B393: No. 388 | C393: 原則 9, 原則 18 | D393: To calm and have grown mindset when receiving negative / improved feedback. | E393: Remain calm and maintain a growth mindset when receiving critical or constructive feedback. | F393: 面對批評或改進意見時，保持冷靜並抱持成長型思維，將其視為進化的養分。 | G393: 聽著別人的批評佮改進意見，莫著急受氣，心神愛穩；抱持成長的心態，共建言當做補足破綻的養分。
A394: Slide 8 | B394: No. 389 | C394: 原則 18 | D394: What do you learn from the past and how to improve in the future. | E394: Regularly ask yourself: "What lessons have I learned from the past, and how can I apply them to improve in the future?" | F394: 時常審視：「我從過去中汲取了什麼教訓？未來該如何改進？」 | G394: 定定自問省思：「我對過去的經驗學著啥物教訓？將來欲按怎改進甲閣較好？」
... A459: Slide 9 | B459: No. 462-2 | C459: 原則 15, 原則 17 | D459: Always prepare your CV updated | E459: Keep your resume and profile continuously updated to remain ready for unexpected opportunities. | F459: 隨時更新個人履歷，保持對職涯機會的敏銳度與準備狀態。 | G459: 家己的履歷表隨時修飾翻新，對外面的機運保持敏銳；好機會一若來，及時伸手掠牢牢。

Sheet 20大核心原則校對
A1: 篇章編號 | B1: 所屬篇章名稱 | C1: 原則編號 | D1: 原則中文名稱 (Title) | E1: 優化英文 (Polished English) | F1: 優化中文 (Polished Mandarin) | G1: 優化台文 (Polished Taiwanese) | H1: 對照卡牌編號 (Card Refs) | I1: 校對狀態 | J1: 修訂建議與批註 | K1: 校對人 | L1: 校對日期
A2: 第 1 篇 | B2: 第一篇：效能與工具（生產力管理） | C2: 原則 1 | D2: 行事曆管理與個人神聖時間 （Calendar Management and Sacred Time） | E2: Schedule all leaves, personal time, business trips, holidays, and routines into your calendar. Reserve buffer time to save brain energy. Shut down your laptop and clean your desk before leaving for a sense of ritual. | F2: 將所有請假、私人時間、公差、節假日及固定行程排入行事曆，保留緩衝時間以節省大腦決策能量。下班前關機並清理桌面，建立儀式感。 | G2: 共請假、私人時間、出差、節日佮固定行程攏排入行事曆，留一寡緩衝時間，大腦才袂傷忝、免逐項代誌費神做決定。落班進前電腦關機、桌頂收予清氣，建立儀式感，心嘛定落來。 | H2: 1, 4, 6, 20, 24, 59, 96, 187, 211, 227, 228, 259, 268, 307, 308, 322, 327, 343, 353, 362, 405, 422
A3: 第 1 篇 | B3: 第一篇：效能與工具（生產力管理） | C3: 原則 2 | D3: 郵件降噪與非同步溝通 （Email Noise Reduction and Focus） | E3: Only read emails where you are mentioned or directly requested to reply. Reduce email frequency（no more than 8 per day）. Use delayed delivery to avoid sending emails during weekends/after-hours, and turn off real-time notifications to focus on core tasks. | F3: 僅閱讀提及自己或有明確回覆要求的信件，減少發信頻率（每日小於 8 封）。利用延遲發送功能，避免在下班或週末發信，並關閉即時通知以維持專注。 | G3: 只讀點名著家己、抑是有指名愛回的信件，發信的次數加減節制（一工莫超過八封）。利用延後寄信的功能，落班抑是歇睏日莫吵別人，即時通知關關咧，心頭專注顧大項代誌。 | H3: 1, 16, 18, 25, 26, 30, 51, 82, 134, 188, 201, 217, 228, 247, 256, 264, 267, 311, 377, 384, 385, 416, 428, 456
A4: 第 1 篇 | B4: 第一篇：效能與工具（生產力管理） | C4: 原則 3 | D4: 工作範本化與流程自動化 （Templatization and Workflow Automation） | E4: Modularize repetitive tasks and create standard templates（e.g., meeting minutes, 8D, yield reports）. Leverage new tools and scripts to automate routine work, aiming for 10x speedup and zero low-level errors. | F4: 將重複性任務模組化，建立標準範本（如會議記錄、8D、Yield 報告）。利用新工具與腳本將常規工作自動化，目標是提升十倍速並降低低級錯誤。 | G4: 照步來的定規代誌做成標準套（親像開會記錄、8D、報告範本）。學用新工具佮腳本共手路自動化，目標是十倍速咧走，手尾清氣閣袂去出粗差。 | H4: 23, 27, 28, 31, 32, 37, 39, 43, 65, 112, 170, 183, 206, 209, 210, 219, 229, 244, 254, 276, 313, 329, 360, 368, 383, 415, 449, 451, 458
A5: 第 1 篇 | B5: 第一篇：效能與工具（生產力管理） | C5: 原則 4 | D5: 數位筆記與知識管理 （Digital Note-taking and Knowledge Management） | E5: Do not rely on memory; build good digital note-taking habits（e.g., using Obsidian or OneNote）. Use clear, descriptive file naming conventions (Product-Stage-Version-Date) and back up regularly to the cloud for fast retrieval. | F5: 不依賴大腦記憶，建立良好的數位筆記習慣（如使用 Obsidian、OneNote）。使用清晰且長檔名的命名規範（產品-階段-版本-日期），並定期備份至雲端以利數秒內檢索。 | G5: 莫數想單靠頭殼記，好記性不如爛筆頭，數位筆記軟體（親像 Obsidian、OneNote）愛用慣勢。檔案名寫予清楚、用長檔名好辨認（產品-階段-版本-日期），照時上雲端備份，幾秒鐘內就揣會著。 | H5: 8, 38, 42, 54, 59, 65, 95, 101, 106, 117, 132, 203, 229, 244, 275, 317, 320, 354, 368, 383, 394, 436, 448
A6: 第 2 篇 | B6: 第二篇：思考與決策（思維模型與問題解決） | C6: 原則 5 | D6: 統計思維與科學驗證 （Statistical Thinking and Scientific Verification） | E6: Support decisions with statistical and objective data（e.g., CPK, confidence interval, normality check） rather than intuition or feeling. Beware of statistical traps (sample bias, unit fallacy, causal fallacy) and interpret data from physical essence. | F6: 用統計與客觀數據（如 CPK、置信區間、常態性檢驗）支持決策，而非憑直覺或感覺。提防統計學中的陷阱（如樣本偏差、比例謬誤、因果謬誤），並從物理本質解釋數據。 | G6: 用數據佮統計（親像 CPK、常態檢驗）來做主裁，莫單靠感覺抑是直覺咧猜。防範數據陷阱（樣本偏差、因果顛倒），代誌著對物理本質摸清楚，數字才講得通。 | H6: 61, 64, 68, 93, 99, 110, 227, 355, 357, 365, 451, 455
A7: 第 2 篇 | B7: 第二篇：思考與決策（思維模型與問題解決） | C7: 原則 6 | D7: 架構化思考與風險控制 （Structured Thinking and Risk Control） | E7: Apply ORID and the Golden Circle（5 Whys） to probe essence. Use Premeditatio Malorum (pre-mortem) for stress testing and black swan prevention. Before deciding, consider consequences after 10 days, 10 months, and 10 years. | F7: 運用 ORID、黃金圈（5 Whys）探究本質，並利用預前驗屍（Premeditatio malorum）進行壓力測試與最壞情況（Black Swan）的防範。決策前思考短期（10天）、中期（10月）與長期（10年）的後果。 | G7: 運用 ORID 佮黃金圈（連問五擺為啥物）挖出根本，凡事用「預前驗屍」拍預防針、想好上歹的烏天鵝局勢來防範。做主裁進前，看遠一寡：十工後、十個月後、十年後到底會變按怎？心肝頭先算盤好。 | H7: 34, 40, 47, 49, 50, 56, 61, 67, 85, 86, 94, 112, 125, 136, 147, 179, 194, 196, 206, 215, 255, 274, 276, 284, 286, 290, 295, 297, 300, 301, 315, 316, 323, 324, 325, 329, 341, 355, 370, 376, 382, 403, 404, 408, 410, 412, 413, 415, 424, 461
A8: 第 2 篇 | B8: 第二篇：思考與決策（思維模型與問題解決） | C8: 原則 7 | D8: 敏捷執行與 MVP 精神 （Done is Better than Perfect） | E8: Build Minimum Viable Products（MVP） and divide big projects into small tasks for phased execution. Fail fast, adjust quickly, and don't let perfectionism delay progress. | F8: 完成勝過完美：推行最小可行產品（MVP），把大專案拆解為小項目並分批執行。快速嘗試、快速失敗（Fast Fail）並及時修正，不要被「一次到位」的完美主義拖延。 | G8: 先做出來，贏過空等完美。大案拆做小步走，先做最小的成果（MVP）試水深。緊試、早知、緊調修，莫予「一擺愛到頂」的執念綁死拖延。 | H8: 15, 45, 100, 111, 155, 163, 241, 286, 287, 306, 314, 347, 351, 356, 363, 367, 374, 375, 409, 458
A9: 第 2 篇 | B9: 第二篇：思考與決策（思維模型與問題解決） | C9: 原則 8 | D9: 以終為始與逆向工程 （Reverse Engineering and Goal Orientation） | E9: Trace execution steps backward from the final goal. Practice reverse thinking: What will happen if we don't do this? Filter out low-value tasks and concentrate resources on the core. | F9: 從最終目標倒推執行步驟。經常進行逆向思考：如果不做這件事，會發生什麼後果？藉此過濾低價值的工作，將資源集中於核心任務。 | G9: 倒踏頭尾看：對最後的成果倒頭算番號、推排路程。定定反轉想：「這件代誌若無做，到底會按怎？」共冗雜無要緊的揀出去，力氣攏集佇核心骨幹。 | H9: 52, 60, 92, 94, 121, 142, 160, 195, 200, 201, 243, 280, 306, 307, 308, 313, 314, 327, 336, 341, 362, 364, 404, 424, 440, 461
A10: 第 3 篇 | B10: 第三篇：溝通與協作（職場對話術） | C10: 原則 9 | D10: 同理與積極對話 （Empathy and Positive Dialogue） | E10: Adopt the Most Respectful Interpretation（MRI） principle. Speak in a gentle and steady tone, using positive phrases instead of defensive words like "but" or "however". Explain complex topics to non-experts or executives in simple, clear terms. | F10: 抱持最善意詮釋（MRI）的原則看待他人溝通，使用溫和穩定的語氣，以正向詞彙（如「我同意你的觀點，而我認為…」）代替否定詞「但是」。用簡單明瞭的話語向非專業或高層解釋複雜事物。 | G10: 凡事向好處想、先用善意量度人（MRI）。講話氣口溫柔定著，加講「我贊同你，另外我按呢看」，莫先講「毋過」閘死人。對大官抑外行的人講話，愈深奧愈愛講大白話。 | H10: 2, 11, 13, 19, 44, 63, 69, 71, 102, 104, 109, 110, 116, 118, 138, 153, 158, 175, 176, 179, 180, 182, 208, 218, 233, 245, 266, 280, 282, 294, 298, 309, 321, 328, 332, 358, 372, 378, 388, 418, 422, 460, 462-1
A11: 第 3 篇 | B11: 第三篇：溝通與協作（職場對話術） | C11: 原則 10 | D11: 會議控制與提問準備 （Meeting Control and Prepared Questioning） | E11: Prepare lists of questions and understand agendas before meetings. Reiterate agreements and next steps before adjourning. Decline meetings that lack value. If an issue involves more than three points, call or meet directly instead of sending back-and-forth emails. | F11: 會前充分準備提問清單、理解議程，並在會議結束前重申共識與下一步行動。人數過多或無實質價值的會議應勇敢拒絕；若溝通事項超過三項，直接通話或見面談，而非來回郵件。 | G11: 開會進前問題清單先備好、議程先讀透，散會進前共共識佮下一步行動重申清楚。人傷濟抑是無實質價值的會愛敢婉拒；若超過三項代誌愛喬，直接敲電話抑是當面參詳，莫佇電子信來來回回冤家。 | H11: 3, 7, 17, 22, 30, 33, 69, 91, 97, 113, 128, 168, 181, 187, 194, 204, 207, 255, 301, 304, 323, 338, 350, 384, 399, 415, 418, 421
A12: 第 3 篇 | B12: 第三篇：溝通與協作（職場對話術） | C12: 原則 11 | D12: 優雅拒絕與沉默邊界 （Classy Refusal and the Boundary of Silence） | E12: Learn to say "no" in a polite, data-backed manner to guard your boundaries. Maintain silence during controversies, avoid commenting on rumors, and do not over-reply to tasks where you are not the DRI. | F12: 學會以體面且數據充分的方式說「不」，並守住自己的工作邊界。在爭議中保持適度沉默，不發表未經證實的言論，也不對非自身 DRI 的事情過度回應。 | G12: 用體面大方、有數據憑據的方式講「不」，顧好家己的工作界線。爭議風波中喙唇皮掠予絚、莫亂開腔，無影無跡的風聲莫批評；毋是家己擔當（非 DRI）的代誌，莫過度回應插手。 | H12: 35, 41, 51, 107, 122, 164, 173, 237, 278, 279, 285, 291, 299, 332, 333, 339, 376, 378, 401, 416, 419, 423
A13: 第 4 篇 | B13: 第四篇：職場生存與防線（自我保護與邊界） | C13: 原則 12 | D13: 自我保護與合規防火牆 （Self-Protection and Compliance Firewall） | E13: Establish defensive documentation habits（meeting minutes, CCB approvals, and email archives） to set up a firewall when errors occur. Stay out of office politics and never complain on public channels. | F13: 建立防禦性的文件化習慣（如保存會議記錄、CCB 審查與電子郵件備份），在同事犯錯或流程出問題時設立防火牆自保。避免介入辦公室政治或在公開渠道抱怨。 | G13: 白紙黑字寫分明、會議記錄收留好（CCB 審查、電子信留底），別人踩雷抑是制度漏氣的時陣，才有證據護身。莫摻入會社的派系政治，公開場合千萬莫大吐苦水。 | H13: 10, 56, 76, 85, 89, 108, 120, 141, 162, 181, 190, 191, 196, 197, 198, 217, 263, 284, 285, 295, 300, 311, 342, 403, 408, 412, 416, 437, 438, 447
... A21: 第 6 篇 | B21: 第六篇：能量、韌性與生活平衡（心智與身心管理） | C21: 原則 20 | D21: 生活平衡與下班儀式 （Life Balance and Post-Work Rituals） | E21: Draw a clear line between work and life; avoid replying to emails or turn off alerts after hours. Schedule 2-3 days of leave regularly to accompany family, travel, or enjoy solo "sacred time." Learn life skills like cooking and invest in personal hobbies. | F21: 將工作與生活邊界劃分清楚，下班後盡量不回郵件或關閉警示。定期規劃 2-3 天的假期陪伴家人、旅行或享受孤獨的「神聖時間」。學習烹飪等生活技能，投資個人興趣，不被工作完全定義。 | G21: 工課佮生活的界線愛分清楚，落班了後莫回信、通知關予恬。定期排兩三工假陪厝內人、出外行行咧，抑是享受孤一个人的「神聖時間」。學煮食等生活手藝、投資個人興趣，人生毋是干焦為著做牛做馬。 | H21: 4, 6, 20, 24, 45, 83, 132, 135, 152, 165, 211, 268, 269, 271, 281, 343, 345, 380, 400, 406, 414, 431, 432, 433, 435, 441, 442, 443, 444, 445, 446

Sheet 篇章核心指引金句 (53則)
A1: 篇章編號 | B1: 所屬篇章名稱 | C1: 金句編號 | D1: 核心指引金句 (Chapter Quote) | E1: 校對狀態 | F1: 修訂建議與批註 | G1: 校對人 | H1: 校對日期
A2: 第 1 篇 | B2: 第一篇：效能與工具（生產力管理） | C2: 金句 1 | D2: ☆利用工具，三觀五覆。☆
A3: 第 1 篇 | B3: 第一篇：效能與工具（生產力管理） | C3: 金句 2 | D3: ☆列表清單，定期巡查。☆
A4: 第 1 篇 | B4: 第一篇：效能與工具（生產力管理） | C4: 金句 3 | D4: ☆科技輔助，多工效應。☆
A5: 第 1 篇 | B5: 第一篇：效能與工具（生產力管理） | C5: 金句 4 | D5: ☆規律原則，自由人生。☆
A6: 第 1 篇 | B6: 第一篇：效能與工具（生產力管理） | C6: 金句 5 | D6: ☆少閣更好，簡省有力。☆
A7: 第 1 篇 | B7: 第一篇：效能與工具（生產力管理） | C7: 金句 6 | D7: ☆排列次序，刪減雜差。☆
A8: 第 2 篇 | B8: 第二篇：思考與決策（思維模型與問題解決） | C8: 金句 1 | D8: ☆毋驚犯錯，風險管理。☆
A9: 第 2 篇 | B9: 第二篇：思考與決策（思維模型與問題解決） | C9: 金句 2 | D9: ☆定定試驗，隨時調整。☆
A10: 第 2 篇 | B10: 第二篇：思考與決策（思維模型與問題解決） | C10: 金句 3 | D10: ☆掠尾揣頭，倒踏順序。☆
A11: 第 2 篇 | B11: 第二篇：思考與決策（思維模型與問題解決） | C11: 金句 4 | D11: ☆分割項目，先有成果。☆
A12: 第 2 篇 | B12: 第二篇：思考與決策（思維模型與問題解決） | C12: 金句 5 | D12: ☆順逆複盤，加乘效用。☆
A13: 第 2 篇 | B13: 第二篇：思考與決策（思維模型與問題解決） | C13: 金句 6 | D13: ☆建構系統，頭著尾是。☆
... A54: 第 6 篇 | B54: 第六篇：能量、韌性與生活平衡（心智與身心管理） | C54: 金句 18 | D54: ☆體驗自然，簡單生活。☆
